setup.py
pymcserver/__init__.py
pymcserver.egg-info/PKG-INFO
pymcserver.egg-info/SOURCES.txt
pymcserver.egg-info/dependency_links.txt
pymcserver.egg-info/requires.txt
pymcserver.egg-info/top_level.txt