Metadata-Version: 1.0
Name: pymcserver
Version: 1.12.26
Summary: MC Server Wrapper
Home-page: UNKNOWN
Author: UNKNOWN
Author-email: UNKNOWN
License: UNKNOWN
Platform: UNKNOWN
